Workbook

Sheet CONTROLE
B2: CONTROLE DE GASTOS MENSAIS
B5: RENDA | C5: JANEIRO | D5: FEVEREIRO | E5: MARÇO | F5: ABRIL | G5: MAIO | H5: JUNHO | I5: JULHO | J5: AGOSTO | K5: SETEMBRO | L5: OUTUBRO | M5: NOVEMBRO | N5: DEZEMBRO | O5: TOTAL
B6: Salário | C6: =SUMIFS(EXTRATO!$F:$F,EXTRATO!$D:$D,CONTROLE!$B6,EXTRATO!$C:$C,CONTROLE!C$5) -> 0 | D6: =SUMIFS(EXTRATO!$F:$F,EXTRATO!$D:$D,CONTROLE!$B6,EXTRATO!$C:$C,CONTROLE!D$5) -> 0 | E6: =SUMIFS(EXTRATO!$F:$F,EXTRATO!$D:$D,CONTROLE!$B6,EXTRATO!$C:$C,CONTROLE!E$5) -> 0 | F6: =SUMIFS(EXTRATO!$F:$F,EXTRATO!$D:$D,CONTROLE!$B6,EXTRATO!$C:$C,CONTROLE!F$5) -> 0 | G6: =SUMIFS(EXTRATO!$F:$F,EXTRATO!$D:$D,CONTROLE!$B6,EXTRATO!$C:$C,CONTROLE!G$5) -> 0 | H6: =SUMIFS(EXTRATO!$F:$F,EXTRATO!$D:$D,CONTROLE!$B6,EXTRATO!$C:$C,CONTROLE!H$5) -> 0 | I6: =SUMIFS(EXTRATO!$F:$F,EXTRATO!$D:$D,CONTROLE!$B6,EXTRATO!$C:$C,CONTROLE!I$5) -> 0 | J6: 0 | K6: 3 | L6: =SUMIFS(EXTRATO!$F:$F,EXTRATO!$D:$D,CONTROLE!$B6,EXTRATO!$C:$C,CONTROLE!L$5) -> 0 | M6: =SUMIFS(EXTRATO!$F:$F,EXTRATO!$D:$D,CONTROLE!$B6,EXTRATO!$C:$C,CONTROLE!M$5) -> 0 | N6: =SUMIFS(EXTRATO!$F:$F,EXTRATO!$D:$D,CONTROLE!$B6,EXTRATO!$C:$C,CONTROLE!N$5) -> 0 | O6: =SUM(C6:N6) -> 3
B7: Renda Extra | C7: =SUMIFS(EXTRATO!$F:$F,EXTRATO!$D:$D,CONTROLE!$B7,EXTRATO!$C:$C,CONTROLE!C$5) -> 0 | D7: =SUMIFS(EXTRATO!$F:$F,EXTRATO!$D:$D,CONTROLE!$B7,EXTRATO!$C:$C,CONTROLE!D$5) -> 0 | E7: =SUMIFS(EXTRATO!$F:$F,EXTRATO!$D:$D,CONTROLE!$B7,EXTRATO!$C:$C,CONTROLE!E$5) -> 0 | F7: =SUMIFS(EXTRATO!$F:$F,EXTRATO!$D:$D,CONTROLE!$B7,EXTRATO!$C:$C,CONTROLE!F$5) -> 0 | G7: =SUMIFS(EXTRATO!$F:$F,EXTRATO!$D:$D,CONTROLE!$B7,EXTRATO!$C:$C,CONTROLE!G$5) -> 0 | H7: =SUMIFS(EXTRATO!$F:$F,EXTRATO!$D:$D,CONTROLE!$B7,EXTRATO!$C:$C,CONTROLE!H$5) -> 0 | I7: =SUMIFS(EXTRATO!$F:$F,EXTRATO!$D:$D,CONTROLE!$B7,EXTRATO!$C:$C,CONTROLE!I$5) -> 0 | J7: 0 | K7: 0 | L7: =SUMIFS(EXTRATO!$F:$F,EXTRATO!$D:$D,CONTROLE!$B7,EXTRATO!$C:$C,CONTROLE!L$5) -> 0 | M7: =SUMIFS(EXTRATO!$F:$F,EXTRATO!$D:$D,CONTROLE!$B7,EXTRATO!$C:$C,CONTROLE!M$5) -> 0 | N7: =SUMIFS(EXTRATO!$F:$F,EXTRATO!$D:$D,CONTROLE!$B7,EXTRATO!$C:$C,CONTROLE!N$5) -> 0 | O7: =SUM(C7:N7) -> 0
B8: Ação | C8: =SUMIFS(EXTRATO!$F:$F,EXTRATO!$D:$D,CONTROLE!$B8,EXTRATO!$C:$C,CONTROLE!C$5) -> 0 | D8: =SUMIFS(EXTRATO!$F:$F,EXTRATO!$D:$D,CONTROLE!$B8,EXTRATO!$C:$C,CONTROLE!D$5) -> 0 | E8: =SUMIFS(EXTRATO!$F:$F,EXTRATO!$D:$D,CONTROLE!$B8,EXTRATO!$C:$C,CONTROLE!E$5) -> 0 | F8: =SUMIFS(EXTRATO!$F:$F,EXTRATO!$D:$D,CONTROLE!$B8,EXTRATO!$C:$C,CONTROLE!F$5) -> 0 | G8: =SUMIFS(EXTRATO!$F:$F,EXTRATO!$D:$D,CONTROLE!$B8,EXTRATO!$C:$C,CONTROLE!G$5) -> 0 | H8: =SUMIFS(EXTRATO!$F:$F,EXTRATO!$D:$D,CONTROLE!$B8,EXTRATO!$C:$C,CONTROLE!H$5) -> 0 | I8: =SUMIFS(EXTRATO!$F:$F,EXTRATO!$D:$D,CONTROLE!$B8,EXTRATO!$C:$C,CONTROLE!I$5) -> 0 | J8: 0 | K8: 2 | L8: =SUMIFS(EXTRATO!$F:$F,EXTRATO!$D:$D,CONTROLE!$B8,EXTRATO!$C:$C,CONTROLE!L$5) -> 0 | M8: =SUMIFS(EXTRATO!$F:$F,EXTRATO!$D:$D,CONTROLE!$B8,EXTRATO!$C:$C,CONTROLE!M$5) -> 0 | N8: =SUMIFS(EXTRATO!$F:$F,EXTRATO!$D:$D,CONTROLE!$B8,EXTRATO!$C:$C,CONTROLE!N$5) -> 0 | O8: =SUM(C8:N8) -> 2
B9: TOTAL | C9: =SUM(C6:C8) -> 0 | D9: =SUM(D6:D8) -> 0 | E9: =SUM(E6:E8) -> 0 | F9: =SUM(F6:F8) -> 0 | G9: =SUM(G6:G8) -> 0 | H9: =SUM(H6:H8) -> 0 | I9: =SUM(I6:I8) -> 0 | J9: =SUM(J6:J8) -> 0 | K9: 0 | L9: 0 | M9: =SUM(M6:M8) -> 0 | N9: =SUM(N6:N8) -> 0 | O9: =SUM(C9:N9) -> 0
B11: GASTOS | C11: JANEIRO | D11: FEVEREIRO | E11: MARÇO | F11: ABRIL | G11: MAIO | H11: JUNHO | I11: JULHO | J11: AGOSTO | K11: SETEMBRO | L11: OUTUBRO | M11: NOVEMBRO | N11: DEZEMBRO | O11: TOTAL
B12: Telefonia | C12: =SUMIFS(EXTRATO!$F:$F,EXTRATO!$D:$D,CONTROLE!$B12,EXTRATO!$C:$C,CONTROLE!C$5) -> 0 | D12: =SUMIFS(EXTRATO!$F:$F,EXTRATO!$D:$D,CONTROLE!$B12,EXTRATO!$C:$C,CONTROLE!D$5) -> 0 | E12: =SUMIFS(EXTRATO!$F:$F,EXTRATO!$D:$D,CONTROLE!$B12,EXTRATO!$C:$C,CONTROLE!E$5) -> 0 | F12: =SUMIFS(EXTRATO!$F:$F,EXTRATO!$D:$D,CONTROLE!$B12,EXTRATO!$C:$C,CONTROLE!F$5) -> 0 | G12: =SUMIFS(EXTRATO!$F:$F,EXTRATO!$D:$D,CONTROLE!$B12,EXTRATO!$C:$C,CONTROLE!G$5) -> 0 | H12: =SUMIFS(EXTRATO!$F:$F,EXTRATO!$D:$D,CONTROLE!$B12,EXTRATO!$C:$C,CONTROLE!H$5) -> 0 | I12: =SUMIFS(EXTRATO!$F:$F,EXTRATO!$D:$D,CONTROLE!$B12,EXTRATO!$C:$C,CONTROLE!I$5) -> 0 | J12: =SUMIFS(EXTRATO!$F:$F,EXTRATO!$D:$D,CONTROLE!$B12,EXTRATO!$C:$C,CONTROLE!L$5) -> 0 | K12: =SUMIFS(EXTRATO!$F:$F,EXTRATO!$D:$D,CONTROLE!$B12,EXTRATO!$C:$C,CONTROLE!L$5) -> 0 | L12: =SUMIFS(EXTRATO!$F:$F,EXTRATO!$D:$D,CONTROLE!$B12,EXTRATO!$C:$C,CONTROLE!L$5) -> 0 | M12: =SUMIFS(EXTRATO!$F:$F,EXTRATO!$D:$D,CONTROLE!$B12,EXTRATO!$C:$C,CONTROLE!M$5) -> 0 | N12: =SUMIFS(EXTRATO!$F:$F,EXTRATO!$D:$D,CONTROLE!$B12,EXTRATO!$C:$C,CONTROLE!N$5) -> 0 | O12: =SUM(C12:N12) -> 0
B13: Diversão | C13: =SUMIFS(EXTRATO!$F:$F,EXTRATO!$D:$D,CONTROLE!$B13,EXTRATO!$C:$C,CONTROLE!C$5) -> 0 | D13: =SUMIFS(EXTRATO!$F:$F,EXTRATO!$D:$D,CONTROLE!$B13,EXTRATO!$C:$C,CONTROLE!D$5) -> 0 | E13: =SUMIFS(EXTRATO!$F:$F,EXTRATO!$D:$D,CONTROLE!$B13,EXTRATO!$C:$C,CONTROLE!E$5) -> 0 | F13: =SUMIFS(EXTRATO!$F:$F,EXTRATO!$D:$D,CONTROLE!$B13,EXTRATO!$C:$C,CONTROLE!F$5) -> 0 | G13: =SUMIFS(EXTRATO!$F:$F,EXTRATO!$D:$D,CONTROLE!$B13,EXTRATO!$C:$C,CONTROLE!G$5) -> 0 | H13: =SUMIFS(EXTRATO!$F:$F,EXTRATO!$D:$D,CONTROLE!$B13,EXTRATO!$C:$C,CONTROLE!H$5) -> 0 | I13: =SUMIFS(EXTRATO!$F:$F,EXTRATO!$D:$D,CONTROLE!$B13,EXTRATO!$C:$C,CONTROLE!I$5) -> 0 | J13: =SUMIFS(EXTRATO!$F:$F,EXTRATO!$D:$D,CONTROLE!$B13,EXTRATO!$C:$C,CONTROLE!L$5) -> 0 | K13: =SUMIFS(EXTRATO!$F:$F,EXTRATO!$D:$D,CONTROLE!$B13,EXTRATO!$C:$C,CONTROLE!L$5) -> 0 | L13: =SUMIFS(EXTRATO!$F:$F,EXTRATO!$D:$D,CONTROLE!$B13,EXTRATO!$C:$C,CONTROLE!L$5) -> 0 | M13: =SUMIFS(EXTRATO!$F:$F,EXTRATO!$D:$D,CONTROLE!$B13,EXTRATO!$C:$C,CONTROLE!M$5) -> 0 | N13: =SUMIFS(EXTRATO!$F:$F,EXTRATO!$D:$D,CONTROLE!$B13,EXTRATO!$C:$C,CONTROLE!N$5) -> 0 | O13: =SUM(C13:N13) -> 0
B14: Doméstico | C14: =SUMIFS(EXTRATO!$F:$F,EXTRATO!$D:$D,CONTROLE!$B14,EXTRATO!$C:$C,CONTROLE!C$5) -> 0 | D14: =SUMIFS(EXTRATO!$F:$F,EXTRATO!$D:$D,CONTROLE!$B14,EXTRATO!$C:$C,CONTROLE!D$5) -> 0 | E14: =SUMIFS(EXTRATO!$F:$F,EXTRATO!$D:$D,CONTROLE!$B14,EXTRATO!$C:$C,CONTROLE!E$5) -> 0 | F14: =SUMIFS(EXTRATO!$F:$F,EXTRATO!$D:$D,CONTROLE!$B14,EXTRATO!$C:$C,CONTROLE!F$5) -> 0 | G14: =SUMIFS(EXTRATO!$F:$F,EXTRATO!$D:$D,CONTROLE!$B14,EXTRATO!$C:$C,CONTROLE!G$5) -> 0 | H14: =SUMIFS(EXTRATO!$F:$F,EXTRATO!$D:$D,CONTROLE!$B14,EXTRATO!$C:$C,CONTROLE!H$5) -> 0 | I14: =SUMIFS(EXTRATO!$F:$F,EXTRATO!$D:$D,CONTROLE!$B14,EXTRATO!$C:$C,CONTROLE!I$5) -> 0 | J14: =SUMIFS(EXTRATO!$F:$F,EXTRATO!$D:$D,CONTROLE!$B14,EXTRATO!$C:$C,CONTROLE!L$5) -> 0 | K14: =SUMIFS(EXTRATO!$F:$F,EXTRATO!$D:$D,CONTROLE!$B14,EXTRATO!$C:$C,CONTROLE!L$5) -> 0 | L14: =SUMIFS(EXTRATO!$F:$F,EXTRATO!$D:$D,CONTROLE!$B14,EXTRATO!$C:$C,CONTROLE!L$5) -> 0 | M14: =SUMIFS(EXTRATO!$F:$F,EXTRATO!$D:$D,CONTROLE!$B14,EXTRATO!$C:$C,CONTROLE!M$5) -> 0 | N14: =SUMIFS(EXTRATO!$F:$F,EXTRATO!$D:$D,CONTROLE!$B14,EXTRATO!$C:$C,CONTROLE!N$5) -> 0 | O14: =SUM(C14:N14) -> 0
B15: Alimentação | C15: =SUMIFS(EXTRATO!$F:$F,EXTRATO!$D:$D,CONTROLE!$B15,EXTRATO!$C:$C,CONTROLE!C$5) -> 0 | D15: =SUMIFS(EXTRATO!$F:$F,EXTRATO!$D:$D,CONTROLE!$B15,EXTRATO!$C:$C,CONTROLE!D$5) -> 0 | E15: =SUMIFS(EXTRATO!$F:$F,EXTRATO!$D:$D,CONTROLE!$B15,EXTRATO!$C:$C,CONTROLE!E$5) -> 0 | F15: =SUMIFS(EXTRATO!$F:$F,EXTRATO!$D:$D,CONTROLE!$B15,EXTRATO!$C:$C,CONTROLE!F$5) -> 0 | G15: =SUMIFS(EXTRATO!$F:$F,EXTRATO!$D:$D,CONTROLE!$B15,EXTRATO!$C:$C,CONTROLE!G$5) -> 0 | H15: =SUMIFS(EXTRATO!$F:$F,EXTRATO!$D:$D,CONTROLE!$B15,EXTRATO!$C:$C,CONTROLE!H$5) -> 0 | I15: =SUMIFS(EXTRATO!$F:$F,EXTRATO!$D:$D,CONTROLE!$B15,EXTRATO!$C:$C,CONTROLE!I$5) -> 0 | J15: =SUMIFS(EXTRATO!$F:$F,EXTRATO!$D:$D,CONTROLE!$B15,EXTRATO!$C:$C,CONTROLE!L$5) -> 0 | K15: =SUMIFS(EXTRATO!$F:$F,EXTRATO!$D:$D,CONTROLE!$B15,EXTRATO!$C:$C,CONTROLE!L$5) -> 0 | L15: =SUMIFS(EXTRATO!$F:$F,EXTRATO!$D:$D,CONTROLE!$B15,EXTRATO!$C:$C,CONTROLE!L$5) -> 0 | M15: =SUMIFS(EXTRATO!$F:$F,EXTRATO!$D:$D,CONTROLE!$B15,EXTRATO!$C:$C,CONTROLE!M$5) -> 0 | N15: =SUMIFS(EXTRATO!$F:$F,EXTRATO!$D:$D,CONTROLE!$B15,EXTRATO!$C:$C,CONTROLE!N$5) -> 0 | O15: =SUM(C15:N15) -> 0
B16: Saúde | C16: =SUMIFS(EXTRATO!$F:$F,EXTRATO!$D:$D,CONTROLE!$B16,EXTRATO!$C:$C,CONTROLE!C$5) -> 0 | D16: =SUMIFS(EXTRATO!$F:$F,EXTRATO!$D:$D,CONTROLE!$B16,EXTRATO!$C:$C,CONTROLE!D$5) -> 0 | E16: =SUMIFS(EXTRATO!$F:$F,EXTRATO!$D:$D,CONTROLE!$B16,EXTRATO!$C:$C,CONTROLE!E$5) -> 0 | F16: =SUMIFS(EXTRATO!$F:$F,EXTRATO!$D:$D,CONTROLE!$B16,EXTRATO!$C:$C,CONTROLE!F$5) -> 0 | G16: =SUMIFS(EXTRATO!$F:$F,EXTRATO!$D:$D,CONTROLE!$B16,EXTRATO!$C:$C,CONTROLE!G$5) -> 0 | H16: =SUMIFS(EXTRATO!$F:$F,EXTRATO!$D:$D,CONTROLE!$B16,EXTRATO!$C:$C,CONTROLE!H$5) -> 0 | I16: =SUMIFS(EXTRATO!$F:$F,EXTRATO!$D:$D,CONTROLE!$B16,EXTRATO!$C:$C,CONTROLE!I$5) -> 0 | J16: =SUMIFS(EXTRATO!$F:$F,EXTRATO!$D:$D,CONTROLE!$B16,EXTRATO!$C:$C,CONTROLE!L$5) -> 0 | K16: =SUMIFS(EXTRATO!$F:$F,EXTRATO!$D:$D,CONTROLE!$B16,EXTRATO!$C:$C,CONTROLE!L$5) -> 0 | L16: =SUMIFS(EXTRATO!$F:$F,EXTRATO!$D:$D,CONTROLE!$B16,EXTRATO!$C:$C,CONTROLE!L$5) -> 0 | M16: =SUMIFS(EXTRATO!$F:$F,EXTRATO!$D:$D,CONTROLE!$B16,EXTRATO!$C:$C,CONTROLE!M$5) -> 0 | N16: =SUMIFS(EXTRATO!$F:$F,EXTRATO!$D:$D,CONTROLE!$B16,EXTRATO!$C:$C,CONTROLE!N$5) -> 0 | O16: =SUM(C16:N16) -> 0
B17: Transporte | C17: =SUMIFS(EXTRATO!$F:$F,EXTRATO!$D:$D,CONTROLE!$B17,EXTRATO!$C:$C,CONTROLE!C$5) -> 0 | D17: =SUMIFS(EXTRATO!$F:$F,EXTRATO!$D:$D,CONTROLE!$B17,EXTRATO!$C:$C,CONTROLE!D$5) -> 0 | E17: =SUMIFS(EXTRATO!$F:$F,EXTRATO!$D:$D,CONTROLE!$B17,EXTRATO!$C:$C,CONTROLE!E$5) -> 0 | F17: =SUMIFS(EXTRATO!$F:$F,EXTRATO!$D:$D,CONTROLE!$B17,EXTRATO!$C:$C,CONTROLE!F$5) -> 0 | G17: =SUMIFS(EXTRATO!$F:$F,EXTRATO!$D:$D,CONTROLE!$B17,EXTRATO!$C:$C,CONTROLE!G$5) -> 0 | H17: =SUMIFS(EXTRATO!$F:$F,EXTRATO!$D:$D,CONTROLE!$B17,EXTRATO!$C:$C,CONTROLE!H$5) -> 0 | I17: =SUMIFS(EXTRATO!$F:$F,EXTRATO!$D:$D,CONTROLE!$B17,EXTRATO!$C:$C,CONTROLE!I$5) -> 0 | J17: =SUMIFS(EXTRATO!$F:$F,EXTRATO!$D:$D,CONTROLE!$B17,EXTRATO!$C:$C,CONTROLE!L$5) -> 0 | K17: =SUMIFS(EXTRATO!$F:$F,EXTRATO!$D:$D,CONTROLE!$B17,EXTRATO!$C:$C,CONTROLE!L$5) -> 0 | L17: =SUMIFS(EXTRATO!$F:$F,EXTRATO!$D:$D,CONTROLE!$B17,EXTRATO!$C:$C,CONTROLE!L$5) -> 0 | M17: =SUMIFS(EXTRATO!$F:$F,EXTRATO!$D:$D,CONTROLE!$B17,EXTRATO!$C:$C,CONTROLE!M$5) -> 0 | N17: =SUMIFS(EXTRATO!$F:$F,EXTRATO!$D:$D,CONTROLE!$B17,EXTRATO!$C:$C,CONTROLE!N$5) -> 0 | O17: =SUM(C17:N17) -> 0
B18: Estudo | C18: =SUMIFS(EXTRATO!$F:$F,EXTRATO!$D:$D,CONTROLE!$B18,EXTRATO!$C:$C,CONTROLE!C$5) -> 0 | D18: =SUMIFS(EXTRATO!$F:$F,EXTRATO!$D:$D,CONTROLE!$B18,EXTRATO!$C:$C,CONTROLE!D$5) -> 0 | E18: =SUMIFS(EXTRATO!$F:$F,EXTRATO!$D:$D,CONTROLE!$B18,EXTRATO!$C:$C,CONTROLE!E$5) -> 0 | F18: =SUMIFS(EXTRATO!$F:$F,EXTRATO!$D:$D,CONTROLE!$B18,EXTRATO!$C:$C,CONTROLE!F$5) -> 0 | G18: =SUMIFS(EXTRATO!$F:$F,EXTRATO!$D:$D,CONTROLE!$B18,EXTRATO!$C:$C,CONTROLE!G$5) -> 0 | H18: =SUMIFS(EXTRATO!$F:$F,EXTRATO!$D:$D,CONTROLE!$B18,EXTRATO!$C:$C,CONTROLE!H$5) -> 0 | I18: =SUMIFS(EXTRATO!$F:$F,EXTRATO!$D:$D,CONTROLE!$B18,EXTRATO!$C:$C,CONTROLE!I$5) -> 0 | J18: =SUMIFS(EXTRATO!$F:$F,EXTRATO!$D:$D,CONTROLE!$B18,EXTRATO!$C:$C,CONTROLE!L$5) -> 0 | K18: =SUMIFS(EXTRATO!$F:$F,EXTRATO!$D:$D,CONTROLE!$B18,EXTRATO!$C:$C,CONTROLE!L$5) -> 0 | L18: =SUMIFS(EXTRATO!$F:$F,EXTRATO!$D:$D,CONTROLE!$B18,EXTRATO!$C:$C,CONTROLE!L$5) -> 0 | M18: =SUMIFS(EXTRATO!$F:$F,EXTRATO!$D:$D,CONTROLE!$B18,EXTRATO!$C:$C,CONTROLE!M$5) -> 0 | N18: =SUMIFS(EXTRATO!$F:$F,EXTRATO!$D:$D,CONTROLE!$B18,EXTRATO!$C:$C,CONTROLE!N$5) -> 0 | O18: =SUM(C18:N18) -> 0
B19: Compras | C19: =SUMIFS(EXTRATO!$F:$F,EXTRATO!$D:$D,CONTROLE!$B19,EXTRATO!$C:$C,CONTROLE!C$5) -> 0 | D19: =SUMIFS(EXTRATO!$F:$F,EXTRATO!$D:$D,CONTROLE!$B19,EXTRATO!$C:$C,CONTROLE!D$5) -> 0 | E19: =SUMIFS(EXTRATO!$F:$F,EXTRATO!$D:$D,CONTROLE!$B19,EXTRATO!$C:$C,CONTROLE!E$5) -> 0 | F19: =SUMIFS(EXTRATO!$F:$F,EXTRATO!$D:$D,CONTROLE!$B19,EXTRATO!$C:$C,CONTROLE!F$5) -> 0 | G19: =SUMIFS(EXTRATO!$F:$F,EXTRATO!$D:$D,CONTROLE!$B19,EXTRATO!$C:$C,CONTROLE!G$5) -> 0 | H19: =SUMIFS(EXTRATO!$F:$F,EXTRATO!$D:$D,CONTROLE!$B19,EXTRATO!$C:$C,CONTROLE!H$5) -> 0 | I19: =SUMIFS(EXTRATO!$F:$F,EXTRATO!$D:$D,CONTROLE!$B19,EXTRATO!$C:$C,CONTROLE!I$5) -> 0 | J19: =SUMIFS(EXTRATO!$F:$F,EXTRATO!$D:$D,CONTROLE!$B19,EXTRATO!$C:$C,CONTROLE!L$5) -> 0 | K19: =SUMIFS(EXTRATO!$F:$F,EXTRATO!$D:$D,CONTROLE!$B19,EXTRATO!$C:$C,CONTROLE!L$5) -> 0 | L19: =SUMIFS(EXTRATO!$F:$F,EXTRATO!$D:$D,CONTROLE!$B19,EXTRATO!$C:$C,CONTROLE!L$5) -> 0 | M19: =SUMIFS(EXTRATO!$F:$F,EXTRATO!$D:$D,CONTROLE!$B19,EXTRATO!$C:$C,CONTROLE!M$5) -> 0 | N19: =SUMIFS(EXTRATO!$F:$F,EXTRATO!$D:$D,CONTROLE!$B19,EXTRATO!$C:$C,CONTROLE!N$5) -> 239 | O19: =SUM(C19:N19) -> 239
B20: TOTAL | C20: =SUM(C12:C19) -> 0 | D20: =SUM(D12:D19) -> 0 | E20: =SUM(E12:E19) -> 0 | F20: =SUM(F12:F19) -> 0 | G20: =SUM(G12:G19) -> 0 | H20: =SUM(H12:H19) -> 0 | I20: =SUM(I12:I19) -> 0 | J20: =SUM(J12:J19) -> 0 | ... N20: =SUM(N12:N19) -> 239 | O20: =SUM(C20:N20) -> 239
B22: SALDO | C22: =C9-C20 -> 0 | D22: =D9-D20 -> 0 | E22: =E9-E20 -> 0 | F22: =F9-F20 -> 0 | G22: =G9-G20 -> 0 | H22: =H9-H20 -> 0 | I22: =I9-I20 -> 0 | J22: =J9-J20 -> 0 | ... N22: =N9-N20 -> -239 | O22: =SUM(C22:N22) -> -239
B23: ACUMULADO | C23: =C22 -> 0 | D23: =C23+D22 -> 0 | E23: =D23+E22 -> 0 | F23: =E23+F22 -> 0 | G23: =F23+G22 -> 0 | H23: =G23+H22 -> 0 | I23: =H23+I22 -> 0 | J23: =I23+J22 -> 0 | K23: =J23+K22 -> 0 | ... N23: =M23+N22 -> -239 | O23: =SUM(C23:N23) -> -239
B24: LIB FINANCEIRA | C24: =C8 -> 0 | D24: =D8 -> 0 | E24: =E8 -> 0 | F24: =F8 -> 0 | G24: =G8 -> 0 | H24: =H8 -> 0 | I24: =I8 -> 0 | J24: =J8 -> 0 | ... N24: =N8 -> 0 | O24: =SUM(C24:N24) -> 2
B25: NECES. BASICA | C25: =SUM(C12,C15,C16,C17) -> 0 | D25: =SUM(D12,D15,D16,D17) -> 0 | E25: =SUM(E12,E15,E16,E17) -> 0 | F25: =SUM(F12,F15,F16,F17) -> 0 | G25: =SUM(G12,G15,G16,G17) -> 0 | H25: =SUM(H12,H15,H16,H17) -> 0 | I25: =SUM(I12,I15,I16,I17) -> 0 | J25: =SUM(J12,J15,J16,J17) -> 0 | ... N25: =SUM(N12,N15,N16,N17) -> 0 | O25: =SUM(C25:N25) -> 0
B26: LAZER | C26: =C13+C19 -> 0 | D26: =D13+D19 -> 0 | E26: =E13+E19 -> 0 | F26: =F13+F19 -> 0 | G26: =G13+G19 -> 0 | H26: =H13+H19 -> 0 | I26: =I13+I19 -> 0 | J26: =J13+J19 -> 0 | ... N26: =N13+N19 -> 239 | O26: =SUM(C26:N26) -> 239
B27: ESTUDO | C27: =C18 -> 0 | D27: =D18 -> 0 | E27: =E18 -> 0 | F27: =F18 -> 0 | G27: =G18 -> 0 | H27: =H18 -> 0 | I27: =I18 -> 0 | J27: =J18 -> 0 | ... N27: =N18 -> 0 | O27: =SUM(C27:N27) -> 0
B30: Total | C30: 1 | D30: = | E30: 10000
B31: Lib Financeira | C31: 0.15 | D31: = | E31: =E30*C31 -> 1500
B32: Estabilidade | C32: 0.1 | D32: = | E32: =C32*E30 -> 1000
B33: Neces. Basicas | C33: 0.55 | D33: = | E33: =C33*E30 -> 5500
B34: Lazer | C34: 0.1 | D34: = | E34: =C34*E30 -> 1000
B35: Estudo | C35: 0.1 | D35: = | E35: =E30*C35 -> 1000

Sheet EXTRATO
B2: Extrato bancário
B4: DATA | C4: MES | D4: CATEGORIAS | E4: DESCRIÇÃO | F4: VALOR
B5: 25/12/2025 | C5: DEZEMBRO | D5: Compras | E5: Just a Test | F5: 239

Sheet CATEGORIAS
B4: CATEGORIAS
B5: Salário
B6: Renda Extra
B7: Ação
B8: Telefonia
B9: Diversão
B10: Doméstico
B11: Alimentação
B12: Saúde
B13: Transporte
B14: Estudo
B15: Compras
